nifti_finder/__init__.py
nifti_finder/explorers/__init__.py
nifti_finder/explorers/base.py
nifti_finder/explorers/core.py
nifti_finder/explorers/mixins.py
nifti_finder/filters/__init__.py
nifti_finder/filters/base.py
nifti_finder/filters/compose.py
nifti_finder/filters/filterable.py
nifti_finder/filters/unit.py
nifti_finder/utils/__init__.py
nifti_finder/utils/io.py
nifti_finder/utils/misc.py
nifti_finder-1.1.0.dist-info/licenses/LICENSE
nifti_finder-1.1.0.dist-info/METADATA
nifti_finder-1.1.0.dist-info/WHEEL
nifti_finder-1.1.0.dist-info/top_level.txt
nifti_finder-1.1.0.dist-info/RECORD
