Metadata-Version: 2.4
Name: nifti-finder
Version: 1.1.0
Summary: Flexible file explorers and filters for navigating neuroimaging datasets and beyond.
Author: Petros Koutsouvelis
License: Apache-2.0
Project-URL: Homepage, https://github.com/pkoutsouvelis/nifti-finder
Project-URL: Repository, https://github.com/pkoutsouvelis/nifti-finder
Project-URL: Issues, https://github.com/pkoutsouvelis/nifti-finder/issues
Keywords: nifti,bids,neuroimaging,file system,data discovery
Classifier: Programming Language :: Python :: 3
Classifier: Programming Language :: Python :: 3 :: Only
Classifier: Programming Language :: Python :: 3.10
Classifier: Programming Language :: Python :: 3.11
Classifier: Programming Language :: Python :: 3.12
Classifier: License :: OSI Approved :: Apache Software License
Classifier: Operating System :: OS Independent
Classifier: Intended Audience :: Science/Research
Classifier: Topic :: Scientific/Engineering
Classifier: Topic :: Scientific/Engineering :: Image Processing
Classifier: Topic :: Utilities
Requires-Python: >=3.10
License-File: LICENSE
Requires-Dist: tqdm<5,>=4.66
Provides-Extra: test
Requires-Dist: pytest>=7.0; extra == "test"
Provides-Extra: dev
Requires-Dist: jupyter>=1.0.0; extra == "dev"
Requires-Dist: pytest>=7.0; extra == "dev"
Requires-Dist: pytest-cov; extra == "dev"
Requires-Dist: ruff; extra == "dev"
Requires-Dist: mypy; extra == "dev"
Requires-Dist: build; extra == "dev"
Requires-Dist: twine; extra == "dev"
Dynamic: license-file
